{"lastUsed":1653301260720,"path":"C:\/Users\/HP\/Desktop\/Eval\/Unit-4","projectCount":1,"recentFiles":[{"path":"\/C1 Eval\/src\/com\/ques2","parentWorkspace":"C:\/Users\/HP\/Desktop\/Eval\/Unit-4","name":"Course.java","lastModified":1653301034256,"locationURI":"file:\/C:\/Users\/HP\/Desktop\/Eval\/Unit-4\/C1%20Eval\/src\/com\/ques2\/Course.java"},{"path":"\/C1 Eval\/src\/com\/ques3","parentWorkspace":"C:\/Users\/HP\/Desktop\/Eval\/Unit-4","name":"CarDetails.java","lastModified":1653300926197,"locationURI":"file:\/C:\/Users\/HP\/Desktop\/Eval\/Unit-4\/C1%20Eval\/src\/com\/ques3\/CarDetails.java"},{"path":"\/C1 Eval\/src\/com\/ques4","parentWorkspace":"C:\/Users\/HP\/Desktop\/Eval\/Unit-4","name":"Main.java","lastModified":1653299551551,"locationURI":"file:\/C:\/Users\/HP\/Desktop\/Eval\/Unit-4\/C1%20Eval\/src\/com\/ques4\/Main.java"},{"path":"\/C1 Eval\/src\/com\/ques5","parentWorkspace":"C:\/Users\/HP\/Desktop\/Eval\/Unit-4","name":"Main.java","lastModified":1653300865776,"locationURI":"file:\/C:\/Users\/HP\/Desktop\/Eval\/Unit-4\/C1%20Eval\/src\/com\/ques5\/Main.java"}]}